{"twofifty":[
{"actwd":"the"},
{"actwd":"of"},
{"actwd":"to"},
{"actwd":"and"},
{"actwd":"a"},
{"actwd":"in"},
{"actwd":"is"},
{"actwd":"it"},
{"actwd":"you"},
{"actwd":"that"},
{"actwd":"he"},
{"actwd":"was"},
{"actwd":"for"},
{"actwd":"on"},
{"actwd":"are"},
{"actwd":"with"},
{"actwd":"as"},
{"actwd":"I"},
{"actwd":"his"},
{"actwd":"they"},
{"actwd":"be"},
{"actwd":"at"},
{"actwd":"one"},
{"actwd":"have"},
{"actwd":"this"},
{"actwd":"from"},
{"actwd":"or"},
{"actwd":"had"},
{"actwd":"by"},
{"actwd":"hot"},
{"actwd":"but"},
{"actwd":"some"},
{"actwd":"what"},
{"actwd":"there"},
{"actwd":"we"},
{"actwd":"can"},
{"actwd":"out"},
{"actwd":"other"},
{"actwd":"were"},
{"actwd":"all"},
{"actwd":"your"},
{"actwd":"when"},
{"actwd":"up"},
{"actwd":"use"},
{"actwd":"word"},
{"actwd":"how"},
{"actwd":"said"},
{"actwd":"an"},
{"actwd":"each"},
{"actwd":"she"},
{"actwd":"which"},
{"actwd":"do"},
{"actwd":"their"},
{"actwd":"time"},
{"actwd":"if"},
{"actwd":"will"},
{"actwd":"way"},
{"actwd":"about"},
{"actwd":"many"},
{"actwd":"then"},
{"actwd":"them"},
{"actwd":"would"},
{"actwd":"write"},
{"actwd":"like"},
{"actwd":"so"},
{"actwd":"these"},
{"actwd":"her"},
{"actwd":"long"},
{"actwd":"make"},
{"actwd":"thing"},
{"actwd":"see"},
{"actwd":"him"},
{"actwd":"two"},
{"actwd":"has"},
{"actwd":"look"},
{"actwd":"more"},
{"actwd":"day"},
{"actwd":"could"},
{"actwd":"go"},
{"actwd":"come"},
{"actwd":"did"},
{"actwd":"my"},
{"actwd":"sound"},
{"actwd":"no"},
{"actwd":"most"},
{"actwd":"number"},
{"actwd":"who"},
{"actwd":"over"},
{"actwd":"know"},
{"actwd":"water"},
{"actwd":"than"},
{"actwd":"call"},
{"actwd":"first"},
{"actwd":"people"},
{"actwd":"may"},
{"actwd":"down"},
{"actwd":"side"},
{"actwd":"been"},
{"actwd":"now"},
{"actwd":"find"},
{"actwd":"any"},
{"actwd":"new"},
{"actwd":"work"},
{"actwd":"part"},
{"actwd":"take"},
{"actwd":"get"},
{"actwd":"place"},
{"actwd":"made"},
{"actwd":"live"},
{"actwd":"where"},
{"actwd":"after"},
{"actwd":"back"},
{"actwd":"little"},
{"actwd":"only"},
{"actwd":"round"},
{"actwd":"man"},
{"actwd":"year"},
{"actwd":"came"},
{"actwd":"show"},
{"actwd":"every"},
{"actwd":"good"},
{"actwd":"me"},
{"actwd":"give"},
{"actwd":"our"},
{"actwd":"under"},
{"actwd":"name"},
{"actwd":"very"},
{"actwd":"through"},
{"actwd":"just"},
{"actwd":"form"},
{"actwd":"much"},
{"actwd":"great"},
{"actwd":"think"},
{"actwd":"say"},
{"actwd":"help"},
{"actwd":"low"},
{"actwd":"line"},
{"actwd":"before"},
{"actwd":"turn"},
{"actwd":"cause"},
{"actwd":"same"},
{"actwd":"mean"},
{"actwd":"differ"},
{"actwd":"move"},
{"actwd":"right"},
{"actwd":"boy"},
{"actwd":"old"},
{"actwd":"too"},
{"actwd":"does"},
{"actwd":"tell"},
{"actwd":"sentence"},
{"actwd":"set"},
{"actwd":"three"},
{"actwd":"want"},
{"actwd":"air"},
{"actwd":"well"},
{"actwd":"also"},
{"actwd":"play"},
{"actwd":"small"},
{"actwd":"end"},
{"actwd":"put"},
{"actwd":"home"},
{"actwd":"read"},
{"actwd":"hand"},
{"actwd":"port"},
{"actwd":"large"},
{"actwd":"spell"},
{"actwd":"add"},
{"actwd":"even"},
{"actwd":"land"},
{"actwd":"here"},
{"actwd":"must"},
{"actwd":"big"},
{"actwd":"high"},
{"actwd":"such"},
{"actwd":"follow"},
{"actwd":"act"},
{"actwd":"why"},
{"actwd":"ask"},
{"actwd":"men"},
{"actwd":"change"},
{"actwd":"went"},
{"actwd":"light"},
{"actwd":"kind"},
{"actwd":"off"},
{"actwd":"need"},
{"actwd":"house"},
{"actwd":"picture"},
{"actwd":"try"},
{"actwd":"us"},
{"actwd":"again"},
{"actwd":"animal"},
{"actwd":"point"},
{"actwd":"mother"},
{"actwd":"world"},
{"actwd":"near"},
{"actwd":"build"},
{"actwd":"self"},
{"actwd":"earth"},
{"actwd":"father"},
{"actwd":"head"},
{"actwd":"stand"},
{"actwd":"own"},
{"actwd":"page"},
{"actwd":"should"},
{"actwd":"country"},
{"actwd":"found"},
{"actwd":"answer"},
{"actwd":"school"},
{"actwd":"grow"},
{"actwd":"study"},
{"actwd":"still"},
{"actwd":"learn"},
{"actwd":"plant"},
{"actwd":"cover"},
{"actwd":"food"},
{"actwd":"sun"},
{"actwd":"four"},
{"actwd":"thought"},
{"actwd":"let"},
{"actwd":"keep"},
{"actwd":"eye"},
{"actwd":"never"},
{"actwd":"last"},
{"actwd":"door"},
{"actwd":"between"},
{"actwd":"city"},
{"actwd":"tree"},
{"actwd":"cross"},
{"actwd":"since"},
{"actwd":"hard"},
{"actwd":"start"},
{"actwd":"might"},
{"actwd":"story"},
{"actwd":"saw"},
{"actwd":"far"},
{"actwd":"sea"},
{"actwd":"draw"},
{"actwd":"left"},
{"actwd":"late"},
{"actwd":"run"},
{"actwd":"don't"},
{"actwd":"while"},
{"actwd":"press"},
{"actwd":"close"},
{"actwd":"night"},
{"actwd":"real"},
{"actwd":"life"},
{"actwd":"few"},
{"actwd":"stop"}
]}